Lab_3/__init__.py
Lab_3/helpers/constants.py
Lab_3/helpers/functions.py
Lab_3/serializers/jsonserializer.py
Lab_3/serializers/xmlserializer.py
JsOnXmLSe814Rializer748-1.2.dist-info/METADATA
JsOnXmLSe814Rializer748-1.2.dist-info/WHEEL
JsOnXmLSe814Rializer748-1.2.dist-info/top_level.txt
JsOnXmLSe814Rializer748-1.2.dist-info/RECORD
