Metadata-Version: 2.1
Name: JsOnXmLSe814Rializer748
Version: 1.2
Summary: Serializer
Home-page: UNKNOWN
Author-email: tatarinov.slava222@gmail.com
License: UNKNOWN
Platform: UNKNOWN
